odoo8_addon_pricelist_item_generator-8.0.1.0.0.99.dev5-py2.7-nspkg.pth
odoo8_addon_pricelist_item_generator-8.0.1.0.0.99.dev5.dist-info/DESCRIPTION.rst
odoo8_addon_pricelist_item_generator-8.0.1.0.0.99.dev5.dist-info/METADATA
odoo8_addon_pricelist_item_generator-8.0.1.0.0.99.dev5.dist-info/RECORD
odoo8_addon_pricelist_item_generator-8.0.1.0.0.99.dev5.dist-info/WHEEL
odoo8_addon_pricelist_item_generator-8.0.1.0.0.99.dev5.dist-info/metadata.json
odoo8_addon_pricelist_item_generator-8.0.1.0.0.99.dev5.dist-info/namespace_packages.txt
odoo8_addon_pricelist_item_generator-8.0.1.0.0.99.dev5.dist-info/top_level.txt
odoo_addons/pricelist_item_generator/README.rst
odoo_addons/pricelist_item_generator/__init__.py
odoo_addons/pricelist_item_generator/__openerp__.py
odoo_addons/pricelist_item_generator/demo/pricelist.item.generator.csv
odoo_addons/pricelist_item_generator/demo/pricelist.item.template.csv
odoo_addons/pricelist_item_generator/demo/pricelist.product.condition.csv
odoo_addons/pricelist_item_generator/i18n/ca.po
odoo_addons/pricelist_item_generator/i18n/de.po
odoo_addons/pricelist_item_generator/i18n/es.po
odoo_addons/pricelist_item_generator/i18n/fr.po
odoo_addons/pricelist_item_generator/i18n/it.po
odoo_addons/pricelist_item_generator/i18n/pricelist_item_generator.pot
odoo_addons/pricelist_item_generator/i18n/sl.po
odoo_addons/pricelist_item_generator/models/__init__.py
odoo_addons/pricelist_item_generator/models/generator.py
odoo_addons/pricelist_item_generator/models/item_template.py
odoo_addons/pricelist_item_generator/models/pricelist.py
odoo_addons/pricelist_item_generator/models/product_condition.py
odoo_addons/pricelist_item_generator/security/ir.model.access.csv
odoo_addons/pricelist_item_generator/static/description/icon.png
odoo_addons/pricelist_item_generator/static/description/img1.png
odoo_addons/pricelist_item_generator/static/description/img2.png
odoo_addons/pricelist_item_generator/static/description/img3.png
odoo_addons/pricelist_item_generator/static/description/pricelist_builder.xcf
odoo_addons/pricelist_item_generator/tests/__init__.py
odoo_addons/pricelist_item_generator/tests/test_generator.py
odoo_addons/pricelist_item_generator/views/pricelist_view.xml
odoo_addons/pricelist_item_generator/views/setting_view.xml
